odoo9_addon_web_readonly_bypass-9.0.1.0.1-py2.7-nspkg.pth
odoo_addons/web_readonly_bypass/__openerp__.py
odoo_addons/web_readonly_bypass/__init__.py
odoo_addons/web_readonly_bypass/README.rst
odoo_addons/web_readonly_bypass/views/readonly_bypass.xml
odoo_addons/web_readonly_bypass/tests/test_js.py
odoo_addons/web_readonly_bypass/tests/__init__.py
odoo_addons/web_readonly_bypass/static/test/web_readonly_bypass.js
odoo_addons/web_readonly_bypass/static/src/js/readonly_bypass.js
odoo9_addon_web_readonly_bypass-9.0.1.0.1.dist-info/top_level.txt
odoo9_addon_web_readonly_bypass-9.0.1.0.1.dist-info/WHEEL
odoo9_addon_web_readonly_bypass-9.0.1.0.1.dist-info/RECORD
odoo9_addon_web_readonly_bypass-9.0.1.0.1.dist-info/metadata.json
odoo9_addon_web_readonly_bypass-9.0.1.0.1.dist-info/DESCRIPTION.rst
odoo9_addon_web_readonly_bypass-9.0.1.0.1.dist-info/METADATA
odoo9_addon_web_readonly_bypass-9.0.1.0.1.dist-info/namespace_packages.txt
