Metadata-Version: 2.0
Name: odoo9-addon-web-readonly-bypass
Version: 9.0.1.0.1
Summary: Allow to save onchange modifications to readonly fields
Home-page: http://www.acsone.eu
Author: UNKNOWN
Author-email: UNKNOWN
License: UNKNOWN
Platform: UNKNOWN
Requires-Dist: odoo (<9.1a,>=9.0a)
Classifier: Programming Language :: Python :: 2.7
Classifier: Framework :: Odoo
